stallar_rpc/__init__.py
stallar_rpc/core.py
stallar_rpc-0.1.0.dist-info/LICENSE
stallar_rpc-0.1.0.dist-info/METADATA
stallar_rpc-0.1.0.dist-info/WHEEL
stallar_rpc-0.1.0.dist-info/RECORD
